flake8_carrot/__init__.py
flake8_carrot/utils.py
flake8_carrot/carrot/CAR101.py
flake8_carrot/carrot/CAR102.py
flake8_carrot/carrot/CAR103.py
flake8_carrot/carrot/CAR104.py
flake8_carrot/carrot/CAR105.py
flake8_carrot/carrot/CAR110.py
flake8_carrot/carrot/CAR111.py
flake8_carrot/carrot/CAR120.py
flake8_carrot/carrot/CAR121.py
flake8_carrot/carrot/CAR122.py
flake8_carrot/carrot/CAR123.py
flake8_carrot/carrot/CAR124.py
flake8_carrot/carrot/CAR140.py
flake8_carrot/carrot/CAR141.py
flake8_carrot/carrot/CAR150.py
flake8_carrot/carrot/CAR151.py
flake8_carrot/carrot/CAR160.py
flake8_carrot/carrot/CAR161.py
flake8_carrot/carrot/CAR162.py
flake8_carrot/carrot/CAR163.py
flake8_carrot/carrot/CAR170.py
flake8_carrot/carrot/CAR180.py
flake8_carrot/carrot/CAR201.py
flake8_carrot/carrot/CAR202.py
flake8_carrot/carrot/CAR301.py
flake8_carrot/carrot/CAR302.py
flake8_carrot/carrot/CAR303.py
flake8_carrot/carrot/CAR304.py
flake8_carrot/carrot/CAR305.py
flake8_carrot/carrot/CAR401.py
flake8_carrot/carrot/CAR501.py
flake8_carrot/carrot/CAR601.py
flake8_carrot/carrot/CAR602.py
flake8_carrot/carrot/CAR610.py
flake8_carrot/carrot/__init__.py
flake8_carrot/tex_bot/__init__.py
flake8_carrot-0.1.8.dist-info/METADATA
flake8_carrot-0.1.8.dist-info/WHEEL
flake8_carrot-0.1.8.dist-info/entry_points.txt
flake8_carrot-0.1.8.dist-info/licenses/LICENSE
flake8_carrot-0.1.8.dist-info/RECORD
