Metadata-Version: 2.4
Name: flake8-carrot
Version: 0.1.8
Summary: A plugin for Flake8; Ensuring that your Python code adheres to CarrotManMatt's opinionated style guide.
Project-URL: Issues, https://github.com/CarrotManMatt/flake8-carrot/issues
Project-URL: Releases, https://github.com/CarrotManMatt/flake8-carrot/releases
Project-URL: Repository, https://github.com/CarrotManMatt/flake8-carrot
Author-email: Matt Norton <matt@carrotmanmatt.com>
License-Expression: Apache-2.0
License-File: LICENSE
Keywords: flake8,flake8-plugin,linter,python,static analysis
Classifier: Development Status :: 4 - Beta
Classifier: Environment :: Console
Classifier: Framework :: Flake8
Classifier: Intended Audience :: Developers
Classifier: Natural Language :: English
Classifier: Operating System :: OS Independent
Classifier: Programming Language :: Python :: 3 :: Only
Classifier: Programming Language :: Python :: 3.14
Classifier: Programming Language :: Python :: 3.15
Classifier: Topic :: Software Development :: Libraries :: Python Modules
Classifier: Topic :: Software Development :: Quality Assurance
Classifier: Typing :: Typed
Requires-Python: >=3.14
Requires-Dist: flake8>=6
Requires-Dist: typed-classproperties>=1.3
